oaas_sdk/__init__.py
oaas_sdk/objects.py
oaas_sdk/sdk.py
oaas_sdk/util.py
oaas_sdk/ws/__init__.py
oaas_sdk/ws/client.py
tests/__init__.py
tests/test_labelingTask.py
tests/test_roundtrip.py
tests/behave/__init__.py
oaas_sdk-1.1.3.dist-info/METADATA
oaas_sdk-1.1.3.dist-info/WHEEL
oaas_sdk-1.1.3.dist-info/top_level.txt
oaas_sdk-1.1.3.dist-info/RECORD
