Metadata-Version: 2.1
Name: oaas-sdk
Version: 1.1.3
Summary: OaaS Client SDK
Home-page: https://github.com/MScienceLLC/oaas_sdk
Author: M Science, LLC
License: UNKNOWN
Platform: UNKNOWN
Classifier: License :: Other/Proprietary License
Classifier: Programming Language :: Python :: 3
Requires-Dist: requests (<3,>=2.7.0)
Requires-Dist: pandas (<1,>=0.24)
Requires-Dist: pyarrow (<1,>=0.15.0)
